iprofile/__init__.py
iprofile/console.py
iprofile/cli/__init__.py
iprofile/cli/activate.py
iprofile/cli/active.py
iprofile/cli/append.py
iprofile/cli/config.py
iprofile/cli/create.py
iprofile/cli/deactivate.py
iprofile/cli/delete.py
iprofile/cli/djshell.py
iprofile/cli/gitignore.py
iprofile/cli/init.py
iprofile/cli/list.py
iprofile/cli/pop.py
iprofile/cli/shell.py
iprofile/core/__init__.py
iprofile/core/config.py
iprofile/core/decorators.py
iprofile/core/utils.py
iprofile/core/models/__init__.py
iprofile/core/models/base.py
iprofile/profiles/__init__.py
iprofile/profiles/utils.py
iprofile/profiles/models/__init__.py
iprofile/profiles/models/base.py
iprofile/profiles/models/mixins.py
iprofile/scripts/__init__.py
iprofile/scripts/django/__init__.py
iprofile/scripts/django/all_models.py
iprofile/scripts/imports/__init__.py
iprofile/scripts/imports/folder.py
iprofile/scripts/imports/profile.py
iprofile/settings/__init__.py
iprofile/settings/registry.py
iprofile/settings/utils.py
iprofile/settings/models/__init__.py
iprofile/settings/models/base.py
iprofile/settings/models/mixins.py
iprofile/texts/__init__.py
iprofile/texts/errors.py
iprofile/texts/helpers.py
iprofile/texts/inputs.py
iprofile/texts/logs.py
iprofile/utils/__init__.py
iprofile/utils/mixins.py
python_iprofile-0.3.3.dist-info/DESCRIPTION.rst
python_iprofile-0.3.3.dist-info/METADATA
python_iprofile-0.3.3.dist-info/RECORD
python_iprofile-0.3.3.dist-info/WHEEL
python_iprofile-0.3.3.dist-info/entry_points.txt
python_iprofile-0.3.3.dist-info/metadata.json
python_iprofile-0.3.3.dist-info/top_level.txt
tests/test_cli/__init__.py
tests/test_cli/test_activate.py
tests/test_cli/test_active.py
tests/test_cli/test_append.py
tests/test_cli/test_config.py
tests/test_cli/test_create.py
tests/test_cli/test_deactivate.py
tests/test_cli/test_delete.py
tests/test_cli/test_djshell.py
tests/test_cli/test_gitignore.py
tests/test_cli/test_init.py
tests/test_cli/test_list.py
tests/test_cli/test_shell.py
tests/test_core/__init__.py
tests/test_core/test_models.py
tests/test_core/test_utils.py
tests/test_profiles/__init__.py
tests/test_profiles/test_models.py
tests/test_profiles/test_utils.py
tests/test_settings/__init__.py
tests/test_settings/test_models.py
