Metadata-Version: 2.0
Name: python-iprofile
Version: 0.3.3
Summary: A CLI for handling IPython 4+ profiles startup scripts.
Home-page: https://github.com/victorfsf/python-iprofile
Author: Victor Ferraz
Author-email: victorfsf.dev@gmail.com
License: UNKNOWN
Keywords: ipython,ipython4,python,python2,python3,shell,profile,iprofile,django
Platform: UNKNOWN
Classifier: Development Status :: 4 - Beta
Classifier: Intended Audience :: Developers
Classifier: License :: OSI Approved :: MIT License
Classifier: Programming Language :: Python :: 2
Classifier: Programming Language :: Python :: 2.7
Classifier: Programming Language :: Python :: 3
Classifier: Programming Language :: Python :: 3.3
Classifier: Programming Language :: Python :: 3.4
Classifier: Programming Language :: Python :: 3.5
Classifier: Framework :: Django
Classifier: Framework :: Django :: 1.7
Classifier: Framework :: Django :: 1.8
Classifier: Framework :: Django :: 1.9
Requires-Dist: PyYAML (==3.11)
Requires-Dist: click (==6.2)
Requires-Dist: glob2 (==0.4.1)
Requires-Dist: ipython (>=4.0.0)
Requires-Dist: python-slugify (==1.2.0)
Requires-Dist: six (==1.10.0)
